<NewDataSet><table><d_codigo>01000</d_codigo><d_asenta>San Ángel</d_asenta><d_tipo_asenta>Colonia</d_tipo_asenta><D_mnpio>Álvaro Obregón</D_mnpio><d_estado>Ciudad de México</d_estado><d_ciudad>Ciudad de México</d_ciudad><d_CP>01001</d_CP><c_estado>09</c_estado><c_oficina>01001</c_oficina><c_CP></c_CP><c_tipo_asenta>09</c_tipo_asenta><c_mnpio>010</c_mnpio><id_asenta_cpcons>0001</id_asenta_cpcons><d_zona>Urbano</d_zona><c_cve_ciudad>01</c_cve_ciudad></table><table><d_codigo>01010</d_codigo><d_asenta>Los Alpes</d_asenta><d_tipo_asenta>Colonia</d_tipo_asenta><D_mnpio>Álvaro Obregón</D_mnpio><d_estado>Ciudad de México</d_estado><d_ciudad>Ciudad de México</d_ciudad><d_CP>01001</d_CP><c_estado>09</c_estado><c_oficina>01001</c_oficina><c_CP></c_CP><c_tipo_asenta>09</c_tipo_asenta><c_mnpio>010</c_mnpio><id_asenta_cpcons>0005</id_asenta_cpcons><d_zona>Urbano</d_zona><c_cve_ciudad>01</c_cve_ciudad></table></NewDataSet>